AUTHORS
LICENSE
MANIFEST.in
README.rst
TODO
setup.py
django_viewtester.egg-info/PKG-INFO
django_viewtester.egg-info/SOURCES.txt
django_viewtester.egg-info/dependency_links.txt
django_viewtester.egg-info/not-zip-safe
django_viewtester.egg-info/requires.txt
django_viewtester.egg-info/top_level.txt
viewtester/__init__.py
viewtester/middleware.py
viewtester/models.py
viewtester/urls.py
viewtester/utils.py
viewtester/views.py
viewtester/management/__init__.py
viewtester/management/commands/__init__.py
viewtester/management/commands/run_viewtester.py
viewtester/templates/viewtester/__init__.py
viewtester/templates/viewtester/boilerplate.txt
viewtester/templates/viewtester/class.txt
viewtester/templates/viewtester/context.txt
viewtester/templates/viewtester/div.html
viewtester/templates/viewtester/extrahead.html
viewtester/templates/viewtester/login.txt
viewtester/templates/viewtester/logout.txt
viewtester/templates/viewtester/request.txt
viewtester/templates/viewtester/status.txt
viewtester/templates/viewtester/test.txt