Metadata-Version: 1.0
Name: django-viewtester
Version: 10.4.3
Summary: A django views-tester
Home-page: http://bitbucket.org/pterk/django-viewtester/
Author: Peter van Kampen
Author-email: pterk@datatailors.com
License: BSD
Platform: UNKNOWN
Classifier: Development Status :: 4 - Beta
Classifier: Framework :: Django
Classifier: Intended Audience :: Developers
Classifier: License :: OSI Approved :: BSD License
Classifier: Operating System :: OS Independent
Classifier: Programming Language :: Python
Classifier: Topic :: Internet :: WWW/HTTP
